{
  "place_id": "ChIJDSbdL7w1K4gRFfmhVE7lBKM",
  "built": "2026-03-12T21:45:39Z",
  "source": "builder-ramen-v2",
  "identity": {
    "place_id": "ChIJDSbdL7w1K4gRFfmhVE7lBKM",
    "name": "Ikkousha Ramen Toronto",
    "city": "Toronto",
    "address": "249 Queen St W, Toronto, ON M5V 1Z4, Canada",
    "type": "restaurant",
    "phone": "(416) 901-2249",
    "website": "https://www.ikkousha.ca/",
    "hours": [
      "Monday: 11:30 AM – 9:30 PM",
      "Tuesday: 11:30 AM – 9:30 PM",
      "Wednesday: 11:30 AM – 9:30 PM",
      "Thursday: 11:30 AM – 9:30 PM",
      "Friday: 11:30 AM – 10:30 PM",
      "Saturday: 11:30 AM – 10:30 PM",
      "Sunday: 11:30 AM – 9:30 PM"
    ],
    "price_level": 2,
    "rating": 4.6,
    "user_rating_count": 2506,
    "menu_link": "https://www.ikkousha.ca/",
    "location": "249 Queen St W, Toronto, ON M5V 1Z4, Canada",
    "lat": 43.6502401,
    "lng": -79.3887656
  },
  "narrative": {
    "summary": "Ramen-focused Toronto spot with strong local following and dependable bowls.",
    "blocks": [
      {
        "id": "b1",
        "title": "Map + Practicals",
        "body": "Start with map and practicals first."
      },
      {
        "id": "b2",
        "title": "Outside",
        "body": "Streetfront + arrival context."
      },
      {
        "id": "b3",
        "title": "Interior vibe",
        "body": "Wide room views and atmosphere."
      },
      {
        "id": "b4",
        "title": "Detailed interior",
        "body": "Close-up design and counter details."
      },
      {
        "id": "b5",
        "title": "Food + drinks",
        "body": "Ramen bowls, sides, and drinks where available."
      },
      {
        "id": "b6",
        "title": "Check",
        "body": "Estimated check for two using Toronto tax logic."
      },
      {
        "id": "block-vibe",
        "type": "vibe",
        "title": "The Vibe",
        "body": "⭐⭐⭐⭐⭐ \"With the frigid temperatures that Toronto is currently experiencing, Ikkousha's Ramen just felt like a nice warm blanket wrap by the fire. We had the Spicy Veg and the Fried chicken and both were excellent! The ingredients felt fresh. The broth very flavorful. The condiments greatly complimentary to the dishes.\n\nThe service was as needed, and the atmosphere was buzzing, a testament to the place. Highly recommend!\"\n\n⭐⭐⭐⭐⭐ \"Very good ramen. I have been trying out many of the options in Toronto and this is one of the best. The unique part about this location as there are two Ikkoushas nearly next to each other. One focused on pork broth and the other on chicken so look closely on the signs outside of each location and pick your preference.\n\nI love tonkotsu broth (pork) in general and this did not disappoint\"\n\n⭐⭐⭐⭐⭐ \"Great everything. Once you enter you feel as the loud streets of Toronto disappear and you are teleported to the quiet streets of Japan. There's soft Japanese music playing in the background. The staff is super friendly. The menu is small 1 small sheet but you really don't need anymore. This was my second or third time trying ramen and I got the basic one with steamed rice and fried chicken. It was perfect. Came within 10 minutes of cooking and when I asked for a fork they polite gave me it. Very nice staff , very tasty food and great atmosphere. If I could give this a 11/10 or even 15/10 it would not give the place justice for how good they are.\""
      }
    ]
  },
  "discovery": {
    "text": "Tokyo-style ramen research",
    "url": "https://www.ikkousha.ca/"
  }
}