{
  "place_id": "PENDING_OPENS_MAR27",
  "source": "disco-sync",
  "identity": {
    "place_id": "PENDING_OPENS_MAR27",
    "name": "Pasta Privato",
    "city": "Toronto",
    "address": "St. Lawrence (next to Notte, 9 Church St)",
    "type": "restaurant"
  },
  "discovery": {
    "text": "Discovered via blogto.com"
  },
  "narrative": {
    "summary": "Hidden 30-seat pasta bar from Yannick Bigourdan & chef Michael Angeloni. $125 tasting or \u00e0 la carte. Opens March 27.",
    "blocks": []
  },
  "type": "restaurant"
}